IslanderDataPreprocessing/DataVisulization.py
IslanderDataPreprocessing/__init__.py
IslanderDataPreprocessing/database.py
IslanderDataPreprocessing/datacorrelation.py
IslanderDataPreprocessing/datadiscovery.py
IslanderDataPreprocessing/encoder2.py
IslanderDataPreprocessing/featur_scaling.py
IslanderDataPreprocessing/missingvalues.py
IslanderDataPreprocessing-2022.1.18.dist-info/LICENSE
IslanderDataPreprocessing-2022.1.18.dist-info/METADATA
IslanderDataPreprocessing-2022.1.18.dist-info/WHEEL
IslanderDataPreprocessing-2022.1.18.dist-info/top_level.txt
IslanderDataPreprocessing-2022.1.18.dist-info/RECORD
