Metadata-Version: 2.1
Name: IslanderDataPreprocessing
Version: 2022.1.18
Summary: module designed to make your data preprocessing experience easier
Home-page: UNKNOWN
Author: Islander Robotics (William McKeon)
Author-email: <IslanderRobotics@gmail.com>
License: UNKNOWN
Keywords: python,machine Learning,Artificial Intelligence,Data Science,Data Cleaning
Platform: UNKNOWN
Classifier: Development Status :: 1 - Planning
Classifier: Intended Audience :: Developers
Classifier: Programming Language :: Python :: 3
Classifier: Operating System :: Unix
Classifier: Operating System :: MacOS :: MacOS X
Classifier: Operating System :: Microsoft :: Windows
License-File: LICENSE
Requires-Dist: pandas
Requires-Dist: matplotlib
Requires-Dist: scikit-learn
Requires-Dist: kaggle
